README.rst
setup.py
Python_JSON_Formatter.egg-info/PKG-INFO
Python_JSON_Formatter.egg-info/SOURCES.txt
Python_JSON_Formatter.egg-info/dependency_links.txt
Python_JSON_Formatter.egg-info/requires.txt
Python_JSON_Formatter.egg-info/top_level.txt
json_formatter/__init__.py