Metadata-Version: 1.0
Name: Python-JSON-Formatter
Version: 0.0.3
Summary: A log formatter for python logging.
Home-page: https://github.com/codeif/Python-JSON-Formatter
Author: codeif
Author-email: me@codeif.com
License: MIT
Platform: UNKNOWN
